README.md
package.json
setup.py
yarn.lock
leverj_exchange_python_bridge/__init__.py
leverj_exchange_python_bridge/api.js
leverj_exchange_python_bridge/api.py
leverj_exchange_python_bridge.egg-info/PKG-INFO
leverj_exchange_python_bridge.egg-info/SOURCES.txt
leverj_exchange_python_bridge.egg-info/dependency_links.txt
leverj_exchange_python_bridge.egg-info/entry_points.txt
leverj_exchange_python_bridge.egg-info/requires.txt
leverj_exchange_python_bridge.egg-info/top_level.txt