Metadata-Version: 2.1
Name: leverj-exchange-python-bridge
Version: 0.1.29
Summary: Python bridge for Leverj.io Spot Exchange
Home-page: http://leverj.io
Author: leverj
License: MIT
Project-URL: Source, https://github.com/leverj/leverj_exchange_python_bridge
Platform: UNKNOWN
Classifier: Programming Language :: Python :: 3
Classifier: License :: OSI Approved :: MIT License
Classifier: Operating System :: OS Independent
Requires-Python: >=3.6
Provides-Extra: dev
